{
    "weeks": [
      {
        "week": "Week 01",
        "links": [
          {
            "url": "week01/holygrail.html",
            "title": "Layout"
          },
          {
            "url": "week01/media-query.html",
            "title": "Media Query"
          },
          {
            "url": "week01/js-pen.html",
            "title": "Js Pen"
          }

        ]
      },
      {
        "week": "Week 02"

      },
      {
        "week": "Week 03"
      },
      {
        "week": "Week 04"
      },
      {
        "week": "Week 05"
      }
    ]
  }
  